rehive/__init__.py
rehive/rehive.py
rehive/api/__init__.py
rehive/api/client.py
rehive/api/exception.py
rehive/api/rehive_util.py
rehive/api/resources/__init__.py
rehive/api/resources/account_definition_resources.py
rehive/api/resources/accounts_resources.py
rehive/api/resources/admin_resources.py
rehive/api/resources/auth_resources.py
rehive/api/resources/base_resources.py
rehive/api/resources/company_resources.py
rehive/api/resources/export_resources.py
rehive/api/resources/metric_resources.py
rehive/api/resources/transaction_resource.py
rehive/api/resources/user_resources.py
rehive-1.2.23.dist-info/LICENSE
rehive-1.2.23.dist-info/METADATA
rehive-1.2.23.dist-info/WHEEL
rehive-1.2.23.dist-info/top_level.txt
rehive-1.2.23.dist-info/RECORD
