Metadata-Version: 2.1
Name: rehive
Version: 1.2.23
Summary: Rehive SDK for Python
Home-page: https://github.com/rehive/rehive-python
Author: Rehive
Author-email: info@rehive.com
License: MIT
Download-URL: https://github.com/rehive/rehive-python/archive/1.2.23.zip
Keywords: rehive api sdk development
Platform: UNKNOWN
Classifier: Development Status :: 4 - Beta
Classifier: Intended Audience :: Developers
Classifier: Topic :: Software Development :: Libraries :: Python Modules
Classifier: License :: OSI Approved :: MIT License
Classifier: Programming Language :: Python :: 3
Classifier: Programming Language :: Python :: 3.3
Classifier: Programming Language :: Python :: 3.4
Classifier: Programming Language :: Python :: 3.5
Requires-Python: >=3.4
License-File: LICENSE
Requires-Dist: requests
